{
  "lead_id": "L000027",
  "geocode": {
    "lat": -12.86577,
    "lon": -36.082889,
    "provider": "PVGIS"
  },
  "territorial": {
    "ibge_ids": {
      "state": "35",
      "city": "3510156"
    },
    "city_name": "Santo André"
  },
  "economics": {
    "bcb_sgs": {
      "inflation": 4.665585791226476
    }
  },
  "irradiance": {
    "provider": "PVGIS",
    "value_kWh_m2_day": 5.2,
    "meta": {
      "tilt": 39,
      "azimuth": 166
    }
  },
  "provenance": [
    "generated"
  ],
  "enriched_at": "2025-04-05T07:04:12.913Z"
}